pymotor/__init__.py
pymotor/conversions.py
pymotor/drivetrain.py
pymotor/files.py
pymotor/motors.py
pymotor/plots.py
pymotor/profiles.py
pymotor-0.3.6.dist-info/METADATA
pymotor-0.3.6.dist-info/RECORD
pymotor-0.3.6.dist-info/WHEEL
pymotor-0.3.6.dist-info/top_level.txt
