Metadata-Version: 2.1
Name: pymotor
Version: 0.3.6
Summary: Generates motion, force and torque profiles for electric motor selection.
Home-page: https://github.com/rmrubin/pymotor
Author: Randy Rubin
Author-email: randymrubin@gmail.com
License: UNKNOWN
Platform: UNKNOWN
Classifier: Development Status :: 3 - Alpha
Classifier: Topic :: Scientific/Engineering :: Physics
Classifier: Programming Language :: Python :: 3
Classifier: License :: OSI Approved :: MIT License
Classifier: Operating System :: OS Independent
Requires-Dist: matplotlib
Requires-Dist: numpy
Requires-Dist: pandas
Requires-Dist: scipy
